{"nodes": [{"id": "p_antydidy_backend_app_db_base_py", "label": "base.py", "file_type": "code", "source_file": "backend/app/db/base.py", "source_location": "L1"}, {"id": "db_base_base", "label": "Base", "file_type": "code", "source_file": "backend/app/db/base.py", "source_location": "L13"}, {"id": "declarativebase", "label": "DeclarativeBase", "file_type": "code", "source_file": "", "source_location": ""}, {"id": "db_base_base_tablename", "label": ".__tablename__()", "file_type": "code", "source_file": "backend/app/db/base.py", "source_location": "L17"}], "edges": [{"source": "p_antydidy_backend_app_db_base_py", "target": "sqlalchemy_orm", "relation": "imports_from", "context": "import", "confidence": "EXTRACTED", "source_file": "backend/app/db/base.py", "source_location": "L1", "weight": 1.0}, {"source": "p_antydidy_backend_app_db_base_py", "target": "sqlalchemy", "relation": "imports_from", "context": "import", "confidence": "EXTRACTED", "source_file": "backend/app/db/base.py", "source_location": "L2", "weight": 1.0}, {"source": "p_antydidy_backend_app_db_base_py", "target": "db_base_base", "relation": "contains", "confidence": "EXTRACTED", "source_file": "backend/app/db/base.py", "source_location": "L13", "weight": 1.0}, {"source": "db_base_base", "target": "declarativebase", "relation": "inherits", "confidence": "EXTRACTED", "source_file": "backend/app/db/base.py", "source_location": "L13", "weight": 1.0}, {"source": "db_base_base", "target": "db_base_base_tablename", "relation": "method", "confidence": "EXTRACTED", "source_file": "backend/app/db/base.py", "source_location": "L17", "weight": 1.0}], "raw_calls": [{"caller_nid": "db_base_base_tablename", "callee": "lower", "is_member_call": true, "source_file": "P:\\antydidy\\backend\\app\\db\\base.py", "source_location": "L19", "receiver": null}]}